pnock.py
pnock-0.1.1.dist-info/DESCRIPTION.rst
pnock-0.1.1.dist-info/METADATA
pnock-0.1.1.dist-info/RECORD
pnock-0.1.1.dist-info/WHEEL
pnock-0.1.1.dist-info/entry_points.txt
pnock-0.1.1.dist-info/metadata.json
pnock-0.1.1.dist-info/top_level.txt
