Metadata-Version: 2.0
Name: pnock
Version: 0.1.1
Summary: Quickly finds which hosts are running a server on a given port on your local network.
Home-page: https://github.com/wildarch/pnock
Author: Daan de Graaf
Author-email: daandegraaf9@gmail.com
License: MIT
Keywords: ssh discover raspberry pi
Platform: UNKNOWN
Classifier: Development Status :: 4 - Beta
Classifier: Intended Audience :: Developers
Classifier: Topic :: System :: Networking
Classifier: License :: OSI Approved :: MIT License
Classifier: Programming Language :: Python :: 2
Classifier: Programming Language :: Python :: 2.7
Classifier: Programming Language :: Python :: 3
Classifier: Programming Language :: Python :: 3.6
